microcrc/__init__.py
microcrc/crc.pyd
microcrc-1.0.3.dist-info/METADATA
microcrc-1.0.3.dist-info/WHEEL
microcrc-1.0.3.dist-info/licenses/LICENSE
microcrc-1.0.3.dist-info/RECORD
