Metadata-Version: 2.4
Name: microcrc
Version: 1.0.3
Summary: Blazing fast CRC32 function for Python.
Project-URL: Documentation, https://github.com/Strangemother/python-microcrc#readme
Project-URL: Homepage, https://github.com/Strangemother/python-microcrc
Project-URL: Repository, https://github.com/Strangemother/python-microcrc
Project-URL: Issues, https://github.com/Strangemother/python-microcrc/issues
Author-email: Strangemother <microcrc@strangemother.com>
License-Expression: MIT
License-File: LICENSE
Classifier: Development Status :: 4 - Beta
Classifier: Programming Language :: Python
Classifier: Programming Language :: Python :: 3.8
Classifier: Programming Language :: Python :: 3.9
Classifier: Programming Language :: Python :: 3.10
Classifier: Programming Language :: Python :: 3.11
Classifier: Programming Language :: Python :: 3.12
Classifier: Programming Language :: Python :: Implementation :: CPython
Classifier: Programming Language :: Python :: Implementation :: PyPy
Requires-Python: >=3.8
